README.md
setup.py
oldage/__init__.py
oldage/_version.py
oldage.egg-info/PKG-INFO
oldage.egg-info/SOURCES.txt
oldage.egg-info/dependency_links.txt
oldage.egg-info/top_level.txt
oldage.egg-info/zip-safe